panday/__init__.py
panday/ci1.py
panday/ci2.py
panday/ci3.py
panday/ci4.py
panday/ci5.py
panday/dc1.py
panday/dc2.py
panday/dc3.py
panday/dc4.py
panday/dc5.py
panday-0.9.5.dist-info/METADATA
panday-0.9.5.dist-info/WHEEL
panday-0.9.5.dist-info/top_level.txt
panday-0.9.5.dist-info/RECORD
